mta/__init__.py
mta/mta.py
mta/data/data.csv.gz
mta-0.0.8.dist-info/METADATA
mta-0.0.8.dist-info/WHEEL
mta-0.0.8.dist-info/top_level.txt
mta-0.0.8.dist-info/RECORD
