Metadata-Version: 2.4
Name: mta
Version: 0.0.8
Summary: Multi-Touch Attribution Models for Marketing Analytics
Home-page: https://github.com/eeghor/mta
Author: Igor Korostil
Author-email: Igor Korostil <eeghor@gmail.com>
License: MIT
Project-URL: Homepage, https://github.com/eeghor/mta
Project-URL: Issues, https://github.com/eeghor/mta/issues
Keywords: attribution,marketing,multi-touch,analytics,markov,shapley
Classifier: Development Status :: 3 - Alpha
Classifier: Intended Audience :: Developers
Classifier: Intended Audience :: Science/Research
Classifier: License :: OSI Approved :: MIT License
Classifier: Programming Language :: Python :: 3.8
Classifier: Programming Language :: Python :: 3.9
Classifier: Programming Language :: Python :: 3.10
Classifier: Programming Language :: Python :: 3.11
Classifier: Programming Language :: Python :: 3.12
Requires-Python: >=3.8
Requires-Dist: pandas>=1.3.0
Requires-Dist: numpy>=1.20.0
Requires-Dist: scikit-learn>=0.24.0
Requires-Dist: arrow>=1.0.0
Dynamic: author
Dynamic: home-page
Dynamic: requires-python
